thundercougarfalconbird/__init__.py
thundercougarfalconbird/models.py
thundercougarfalconbird/sensors.py
thundercougarfalconbird/simple.py
thundercougarfalconbird/uav.py
thundercougarfalconbird-0.0.4.dist-info/LICENSE
thundercougarfalconbird-0.0.4.dist-info/WHEEL
thundercougarfalconbird-0.0.4.dist-info/METADATA
thundercougarfalconbird-0.0.4.dist-info/RECORD
